[
  {
    "id": "app_ef74a44d",
    "title": "Marriage memories (Abed Ali)",
    "description": "11 items in this album.",
    "link": "",
    "image": "https://res.cloudinary.com/dpbuhcvui/raw/upload/v1776666559/IMG_2353.jpeg",
    "category": "Albums",
    "version": "1.0",
    "is_album": true,
    "album_files": [
      {
        "name": "IMG_2353.jpeg",
        "link": "https://res.cloudinary.com/dpbuhcvui/raw/upload/v1776666559/IMG_2353.jpeg"
      },
      {
        "name": "IMG_2352.jpeg",
        "link": "https://res.cloudinary.com/dpbuhcvui/raw/upload/v1776666568/IMG_2352.jpeg"
      },
      {
        "name": "IMG_2350.jpeg",
        "link": "https://res.cloudinary.com/dpbuhcvui/raw/upload/v1776666614/IMG_2350.jpeg"
      },
      {
        "name": "IMG_2346.jpeg",
        "link": "https://res.cloudinary.com/dpbuhcvui/raw/upload/v1776666620/IMG_2346.jpeg"
      },
      {
        "name": "IMG_2343.jpeg",
        "link": "https://res.cloudinary.com/dpbuhcvui/raw/upload/v1776666627/IMG_2343.jpeg"
      },
      {
        "name": "IMG_2342.jpeg",
        "link": "https://res.cloudinary.com/dpbuhcvui/raw/upload/v1776666634/IMG_2342.jpeg"
      },
      {
        "name": "IMG_2341.jpeg",
        "link": "https://res.cloudinary.com/dpbuhcvui/raw/upload/v1776666642/IMG_2341.jpeg"
      },
      {
        "name": "IMG_2338.jpeg",
        "link": "https://res.cloudinary.com/dpbuhcvui/raw/upload/v1776666648/IMG_2338.jpeg"
      },
      {
        "name": "IMG_2337.jpeg",
        "link": "https://res.cloudinary.com/dpbuhcvui/raw/upload/v1776666654/IMG_2337.jpeg"
      },
      {
        "name": "IMG_2335.jpeg",
        "link": "https://res.cloudinary.com/dpbuhcvui/raw/upload/v1776666661/IMG_2335.jpeg"
      },
      {
        "name": "IMG_2334.jpeg",
        "link": "https://res.cloudinary.com/dpbuhcvui/raw/upload/v1776666668/IMG_2334.jpeg"
      }
    ]
  }
]